MANIFEST.in
README.txt
setup.py
phenomena/__init__.py
phenomena/command_message.py
phenomena/config_lock.py
phenomena/connection_manager.py
phenomena/controller.py
phenomena/event_core.py
phenomena/string_to_ontic.py
phenomena.egg-info/PKG-INFO
phenomena.egg-info/SOURCES.txt
phenomena.egg-info/dependency_links.txt
phenomena.egg-info/requires.txt
phenomena.egg-info/top_level.txt
phenomena/connection_types/__init__.py
phenomena/connection_types/listener.py
phenomena/connection_types/requester.py
phenomena/connection_types/responder.py
phenomena/connection_types/sink.py
test/test_utils.py