Metadata-Version: 1.1
Name: phenomena
Version: 0.0.2
Summary: Being of Beings
Home-page: https://github.com/neoinsanity/phenomena
Author: Raul Gonzalez
Author-email: mindbender@gmail.com
License: Apache License 2.0
Platform: UNKNOWN
Classifier: Development Status :: 3 - Alpha
Classifier: Intended Audience :: Developers
Classifier: License :: OSI Approved :: Apache Software License
Classifier: Operating System :: OS Independent
Classifier: Programming Language :: Python :: 2.7
Classifier: Programming Language :: Python :: 3
Classifier: Topic :: Software Development
